acltldr/__init__.py
acltldr/main.py
acltldr/utils.py
acltldr-0.1.1.dist-info/entry_points.txt
acltldr-0.1.1.dist-info/WHEEL
acltldr-0.1.1.dist-info/METADATA
acltldr-0.1.1.dist-info/RECORD
